config.py
ingest_folder.py
query_rag.py
classes/OCRProcessor.py
classes/ProcessingConfig.py
pyragix-0.4.1.dist-info/METADATA
pyragix-0.4.1.dist-info/WHEEL
pyragix-0.4.1.dist-info/entry_points.txt
pyragix-0.4.1.dist-info/top_level.txt
pyragix-0.4.1.dist-info/RECORD
