Metadata-Version: 2.4
Name: pyragix
Version: 0.4.1
Summary: A document ingestion and RAG query system with FAISS indexing and OCR support
Author-email: psarno <psarno@users.noreply.github.com>
License-Expression: MIT
Project-URL: Homepage, https://github.com/psarno/PyRagix
Project-URL: Repository, https://github.com/psarno/PyRagix
Project-URL: Issues, https://github.com/psarno/PyRagix/issues
Classifier: Development Status :: 3 - Alpha
Classifier: Intended Audience :: Developers
Classifier: Programming Language :: Python :: 3
Classifier: Programming Language :: Python :: 3.13
Requires-Python: >=3.13
Requires-Dist: torch>=2.9.0
Requires-Dist: transformers>=4.57.1
Requires-Dist: sentence-transformers>=5.1.2
Requires-Dist: huggingface-hub>=0.20.0
Requires-Dist: tokenizers>=0.22.1
Requires-Dist: faiss-cpu>=1.12.0
Requires-Dist: paddleocr>=3.3.0
Requires-Dist: paddlepaddle>=3.2.0
Requires-Dist: pillow>=12.0.0
Requires-Dist: numpy>=2.3.4
Requires-Dist: requests>=2.32.5
Requires-Dist: tenacity>=9.0.0
Requires-Dist: fastapi>=0.120.0
Requires-Dist: uvicorn[standard]>=0.38.0
Requires-Dist: beautifulsoup4>=4.14.2
Requires-Dist: lxml>=6.0.2
Requires-Dist: psutil>=7.1.2
Requires-Dist: rank-bm25>=0.2.2
Requires-Dist: sqlite-utils>=3.38
Requires-Dist: pymupdf>=1.26.5
Requires-Dist: langchain-text-splitters>=1.0.0
Requires-Dist: pydantic>=2.12.3
Requires-Dist: types-requests>=2.32.4.20250913
Requires-Dist: scikit-learn>=1.7.2
Requires-Dist: umap-learn>=0.5.9
Provides-Extra: dev
Requires-Dist: ruff>=0.14.2; extra == "dev"
Requires-Dist: pytest>=8.4.2; extra == "dev"
Requires-Dist: twine; extra == "dev"
Requires-Dist: build; extra == "dev"
Requires-Dist: pyright>=1.1.407; extra == "dev"
